{
  "configurations": [
    {
      "browse": {
        "databaseFilename": "${default}",
        "limitSymbolsToIncludedHeaders": false
      },
      "includePath": [
        "/opt/ros/noetic/include/**",
        "/home/ty/Desktop/genetic_recombination/src/a02_scout_car_task_1/include/**",
        "/home/ty/Desktop/my_catkin_ws/src/opencv_study/include/**",
        "/home/ty/Desktop/my_catkin_ws/src/pcl_study/include/**",
        "/usr/include/**"
      ],
      "name": "ROS",
      "intelliSenseMode": "gcc-arm64",
      "compilerPath": "/usr/bin/gcc",
      "cStandard": "gnu11",
      "cppStandard": "c++14"
    }
  ],
  "version": 4
}